py122u/__init__.py
py122u/error.py
py122u/nfc.py
py122u/option.py
py122u/utils.py
py122u-2.3.5.dist-info/LICENSE
py122u-2.3.5.dist-info/METADATA
py122u-2.3.5.dist-info/WHEEL
py122u-2.3.5.dist-info/top_level.txt
py122u-2.3.5.dist-info/RECORD
