Metadata-Version: 2.1
Name: py122u
Version: 2.3.5
Summary: This is a python library for the ACR122U NFC reader
Author-email: Brice PARENT <briceparent.it@gmail.com>, Robert van Dijk <contact@robertvandijk.nl>
License: MIT License
Project-URL: Homepage, https://github.com/Flowtter/py-acr122u
Keywords: nfc,acr,acr122u
Classifier: License :: OSI Approved :: MIT License
Classifier: Programming Language :: Python
Classifier: Programming Language :: Python :: 3
Requires-Python: >=3.8
License-File: LICENSE
Requires-Dist: pyscard >=2.0.7
Provides-Extra: dev
Requires-Dist: black ; extra == 'dev'
Requires-Dist: bumpver ; extra == 'dev'
Requires-Dist: isort ; extra == 'dev'
Requires-Dist: pip-tools ; extra == 'dev'
Requires-Dist: pytest ; extra == 'dev'
Requires-Dist: pytest-mock ; extra == 'dev'
